sdk/__init__.py
sdk/config.py
sdk/detector.py
sdk/face_mask_detector.py
sdk/utils.py
face_mask_sdk-0.1.0.dist-info/METADATA
face_mask_sdk-0.1.0.dist-info/WHEEL
face_mask_sdk-0.1.0.dist-info/top_level.txt
face_mask_sdk-0.1.0.dist-info/RECORD
