Metadata-Version: 2.4
Name: face_mask_sdk
Version: 0.1.0
Summary: 一个用于口罩检测的Python SDK
Home-page: https://github.com/yourusername/face_mask_sdk
Author: Your Name
Author-email: your.email@example.com
Classifier: Programming Language :: Python :: 3
Classifier: License :: OSI Approved :: MIT License
Classifier: Operating System :: OS Independent
Requires-Python: >=3.8
Requires-Dist: opencv-python>=4.8.0
Requires-Dist: numpy>=1.24.0
Requires-Dist: ultralytics>=8.0.0
Requires-Dist: mediapipe>=0.10.0
Requires-Dist: scipy>=1.10.0
Dynamic: author
Dynamic: author-email
Dynamic: classifier
Dynamic: description
Dynamic: description-content-type
Dynamic: home-page
Dynamic: requires-dist
Dynamic: requires-python
Dynamic: summary
